<?xml version="1.0" encoding="UTF-8" standalone="yes"?>
<w:glossaryDocument xmlns:wpc="http://schemas.microsoft.com/office/word/2010/wordprocessingCanvas" xmlns:mc="http://schemas.openxmlformats.org/markup-compatibility/2006" xmlns:o="urn:schemas-microsoft-com:office:office" xmlns:r="http://schemas.openxmlformats.org/officeDocument/2006/relationships" xmlns:m="http://schemas.openxmlformats.org/officeDocument/2006/math" xmlns:v="urn:schemas-microsoft-com:vml" xmlns:wp14="http://schemas.microsoft.com/office/word/2010/wordprocessingDrawing" xmlns:wp="http://schemas.openxmlformats.org/drawingml/2006/wordprocessingDrawing" xmlns:w10="urn:schemas-microsoft-com:office:word" xmlns:w="http://schemas.openxmlformats.org/wordprocessingml/2006/main" xmlns:w14="http://schemas.microsoft.com/office/word/2010/wordml" xmlns:w15="http://schemas.microsoft.com/office/word/2012/wordml" xmlns:wpg="http://schemas.microsoft.com/office/word/2010/wordprocessingGroup" xmlns:wpi="http://schemas.microsoft.com/office/word/2010/wordprocessingInk" xmlns:wne="http://schemas.microsoft.com/office/word/2006/wordml" xmlns:wps="http://schemas.microsoft.com/office/word/2010/wordprocessingShape" mc:Ignorable="w14 w15 wp14"><w:docParts><w:docPart><w:docPartPr><w:name w:val="VSCVerbatimSampleCard"/><w:style w:val="Heading 4"/><w:category><w:name w:val="General"/><w:gallery w:val="autoTxt"/></w:category><w:behaviors><w:behavior w:val="content"/></w:behaviors><w:guid w:val="{BE7F2A50-CF4D-6946-821B-4BC816F93DB7}"/></w:docPartPr><w:docPartBody><w:p w:rsidR="00F4418D" w:rsidRDefault="00F4418D" w:rsidP="00F4418D"><w:pPr><w:pStyle w:val="Heading4"/></w:pPr><w:r><w:t>This is a sample card</w:t></w:r></w:p><w:p w:rsidR="00F4418D" w:rsidRDefault="00F4418D" w:rsidP="00F4418D"><w:r><w:t xml:space="preserve">First </w:t></w:r><w:r w:rsidRPr="005870E8"><w:rPr><w:rStyle w:val="Style13ptBold"/></w:rPr><w:t>Last</w:t></w:r><w:r><w:t>, qualifications, 1-1-</w:t></w:r><w:r w:rsidRPr="005870E8"><w:rPr><w:rStyle w:val="Style13ptBold"/></w:rPr><w:t>2014</w:t></w:r><w:r><w:t>, “This is an article title,” Publication, http://url.com</w:t></w:r></w:p><w:p w:rsidR="00F4418D" w:rsidRDefault="00F4418D" w:rsidP="00F4418D"><w:r><w:rPr><w:rStyle w:val="StyleUnderline"/><w:highlight w:val="yellow"/></w:rPr><w:t>This is sample card tex</w:t></w:r><w:r w:rsidRPr="005870E8"><w:rPr><w:rStyle w:val="StyleUnderline"/><w:highlight w:val="yellow"/></w:rPr><w:t>t this is sample card text this is sample card text this is sample card text.</w:t></w:r><w:r><w:t xml:space="preserve"> This will be hidden this will be hidden this will be hidden this will be hidden this will be hidden this will be hidden this will be hidden this will be hidden this will be hidden. </w:t></w:r><w:r w:rsidRPr="005870E8"><w:rPr><w:rStyle w:val="StyleUnderline"/><w:highlight w:val="yellow"/></w:rPr><w:t>This is sample card text this is sample card text this is sample card text this is sample card text this is sample card text this is sample card text this is sample card text this is sample card text this is sample card text this is sample card text this is sample card text.</w:t></w:r><w:r><w:t xml:space="preserve"> This will be hidden this will be hidden this will be hidden this will be hidden this will be hidden this will be hidden this will be hidden this will be hidden this will be hidden. This will be hidden this will be hidden. This will be hidden this will be hidden this will be hidden this will be hidden this will be hidden this will be hidden this will be hidden. This will be hidden this will be hidden this will be hidden this will be hidden. This will be hidden this will be hidden this will be hidden this will be hidden this will be hidden. This will be hidden this will be hidden this will be hidden this will be hidden this will be hidden this will be hidden this will be hidden. This will be hidden this will be hidden. </w:t></w:r><w:r w:rsidRPr="005870E8"><w:rPr><w:rStyle w:val="StyleUnderline"/><w:highlight w:val="yellow"/></w:rPr><w:t>This is sample card text this is sample card text this is sample card text this is sample card text this is sample card text this is sample card text this is sample card text this is sample card text this is sample card text this is sample card text this is sample card text this is sample card text this is sample card text this is sample card text this is sample card text.</w:t></w:r></w:p><w:p w:rsidR="00F4418D" w:rsidRDefault="00F4418D"/></w:docPartBody></w:docPart></w:docParts></w:glossaryDocument>